{
  "name": "Empty L-System",
  "drawing_parameters": {
    "start_position": [
      -0.25,
      0.25
    ],
    "start_angle": 0.0,
    "angle_delta": 0,
    "step": 0.1,
    "color_palette_size": 1,
    "initial_line_width": 1.0,
    "line_width_delta": 0.1
  },
  "modify_camera": false,
  "camera_radius": 0.0,
  "camera_phi": 0.0,
  "camera_theta": 0.0,
  "axiom": "",
  "seed": 0,
  "iteration_depth": 1,
  "rules": [
  ],
  "interpretations": [
  ],
  "color_palette": [
    [
      1.0,
      1.0,
      1.0
    ]
  ]
}

